pyviz_comms/__init__.py
pyviz_comms/_version.py
pyviz_comms/notebook.js
pyviz_comms/labextension/package.json
pyviz_comms/labextension/schemas/@pyviz/jupyterlab_pyviz/package.json.orig
pyviz_comms/labextension/schemas/@pyviz/jupyterlab_pyviz/plugin.json
pyviz_comms/labextension/static/30.daddcd1b31fcf027b32b.js
pyviz_comms/labextension/static/479.f8613002a4a279797a83.js
pyviz_comms/labextension/static/747.9aeb343e85f683c2e81e.js
pyviz_comms/labextension/static/remoteEntry.c8393541423362724be3.js
pyviz_comms/labextension/static/style.js
pyviz_comms/labextension/static/third-party-licenses.json
pyviz_comms/tests/__init__.py
pyviz_comms/tests/test_extension.py
pyviz_comms-3.0.2.data/data/share/jupyter/labextensions/@pyviz/jupyterlab_pyviz/package.json
pyviz_comms-3.0.2.data/data/share/jupyter/labextensions/@pyviz/jupyterlab_pyviz/schemas/@pyviz/jupyterlab_pyviz/package.json.orig
pyviz_comms-3.0.2.data/data/share/jupyter/labextensions/@pyviz/jupyterlab_pyviz/schemas/@pyviz/jupyterlab_pyviz/plugin.json
pyviz_comms-3.0.2.data/data/share/jupyter/labextensions/@pyviz/jupyterlab_pyviz/static/30.daddcd1b31fcf027b32b.js
pyviz_comms-3.0.2.data/data/share/jupyter/labextensions/@pyviz/jupyterlab_pyviz/static/479.f8613002a4a279797a83.js
pyviz_comms-3.0.2.data/data/share/jupyter/labextensions/@pyviz/jupyterlab_pyviz/static/747.9aeb343e85f683c2e81e.js
pyviz_comms-3.0.2.data/data/share/jupyter/labextensions/@pyviz/jupyterlab_pyviz/static/remoteEntry.c8393541423362724be3.js
pyviz_comms-3.0.2.data/data/share/jupyter/labextensions/@pyviz/jupyterlab_pyviz/static/style.js
pyviz_comms-3.0.2.data/data/share/jupyter/labextensions/@pyviz/jupyterlab_pyviz/static/third-party-licenses.json
pyviz_comms-3.0.2.dist-info/METADATA
pyviz_comms-3.0.2.dist-info/WHEEL
pyviz_comms-3.0.2.dist-info/licenses/LICENSE
pyviz_comms-3.0.2.dist-info/licenses/LICENSE.txt
pyviz_comms-3.0.2.dist-info/RECORD
