Metadata-Version: 2.3
Name: pyviz_comms
Version: 3.0.2
Dynamic: Keywords
Summary: A JupyterLab extension for rendering HoloViz content.
Project-URL: Homepage, https://github.com/holoviz/pyviz_comms
Project-URL: Bug Tracker, https://github.com/holoviz/pyviz_comms/issues
Project-URL: Repository, https://github.com/holoviz/pyviz_comms.git
Author: Philipp Rudiger
Maintainer-email: HoloViz <developers@holoviz.org>
License: BSD 3-Clause License
License-File: LICENSE
License-File: LICENSE.txt
Classifier: Development Status :: 5 - Production/Stable
Classifier: Framework :: Jupyter
Classifier: Framework :: Jupyter :: JupyterLab
Classifier: Framework :: Jupyter :: JupyterLab :: 4
Classifier: Framework :: Jupyter :: JupyterLab :: Extensions
Classifier: Framework :: Jupyter :: JupyterLab :: Extensions :: Prebuilt
Classifier: Intended Audience :: Developers
Classifier: Intended Audience :: Science/Research
Classifier: License :: OSI Approved :: BSD License
Classifier: Natural Language :: English
Classifier: Operating System :: OS Independent
Classifier: Programming Language :: Python
Classifier: Programming Language :: Python :: 3
Classifier: Programming Language :: Python :: 3.8
Classifier: Programming Language :: Python :: 3.9
Classifier: Programming Language :: Python :: 3.10
Classifier: Programming Language :: Python :: 3.11
Classifier: Topic :: Scientific/Engineering
Classifier: Topic :: Software Development :: Libraries
Requires-Python: >=3.8
Requires-Dist: param
Provides-Extra: all
Requires-Dist: pyviz-comms[build]; extra == 'all'
Requires-Dist: pyviz-comms[tests]; extra == 'all'
Provides-Extra: build
Requires-Dist: jupyterlab~=4.0; extra == 'build'
Requires-Dist: keyring; extra == 'build'
Requires-Dist: rfc3986; extra == 'build'
Requires-Dist: setuptools>=40.8.0; extra == 'build'
Requires-Dist: twine; extra == 'build'
Provides-Extra: tests
Requires-Dist: flake8; extra == 'tests'
Requires-Dist: pytest; extra == 'tests'
